progressive_blur/__init__.py
progressive_blur/cli.py
progressive_blur/core.py
progressive_blur/utils.py
progressive_blur-1.0.0.dist-info/LICENSE
progressive_blur-1.0.0.dist-info/METADATA
progressive_blur-1.0.0.dist-info/WHEEL
progressive_blur-1.0.0.dist-info/entry_points.txt
progressive_blur-1.0.0.dist-info/top_level.txt
progressive_blur-1.0.0.dist-info/RECORD
