Metadata-Version: 2.1
Name: progressive-blur
Version: 1.0.0
Summary: A high-quality Python library for applying progressive blur effects to images
Author-email: Ali Maasoglu <ali@example.com>
License: MIT
Project-URL: Homepage, https://github.com/almmaasoglu/python-progressive-blur
Project-URL: Documentation, https://github.com/almmaasoglu/python-progressive-blur#readme
Project-URL: Repository, https://github.com/almmaasoglu/python-progressive-blur.git
Project-URL: Bug Tracker, https://github.com/almmaasoglu/python-progressive-blur/issues
Keywords: image,blur,progressive,gradient,image-processing,PIL,computer-vision
Classifier: Development Status :: 5 - Production/Stable
Classifier: Intended Audience :: Developers
Classifier: Intended Audience :: End Users/Desktop
Classifier: Operating System :: OS Independent
Classifier: Programming Language :: Python :: 3
Classifier: Programming Language :: Python :: 3.8
Classifier: Programming Language :: Python :: 3.9
Classifier: Programming Language :: Python :: 3.10
Classifier: Programming Language :: Python :: 3.11
Classifier: Programming Language :: Python :: 3.12
Classifier: Topic :: Multimedia :: Graphics
Classifier: Topic :: Multimedia :: Graphics :: Graphics Conversion
Classifier: Topic :: Scientific/Engineering :: Image Processing
Classifier: Topic :: Software Development :: Libraries :: Python Modules
Requires-Python: >=3.8
License-File: LICENSE
Requires-Dist: Pillow >=9.0.0
Requires-Dist: numpy >=1.21.0
Requires-Dist: typing-extensions >=4.0.0 ; python_version < "3.10"
Provides-Extra: benchmark
Requires-Dist: matplotlib >=3.5.0 ; extra == 'benchmark'
Requires-Dist: seaborn >=0.11.0 ; extra == 'benchmark'
Requires-Dist: memory-profiler >=0.60.0 ; extra == 'benchmark'
Provides-Extra: dev
Requires-Dist: pytest >=7.0.0 ; extra == 'dev'
Requires-Dist: pytest-cov >=4.0.0 ; extra == 'dev'
Requires-Dist: black >=22.0.0 ; extra == 'dev'
Requires-Dist: isort >=5.10.0 ; extra == 'dev'
Requires-Dist: flake8 >=5.0.0 ; extra == 'dev'
Requires-Dist: mypy >=1.0.0 ; extra == 'dev'
Requires-Dist: pre-commit >=2.20.0 ; extra == 'dev'
Provides-Extra: docs
Requires-Dist: sphinx >=5.0.0 ; extra == 'docs'
Requires-Dist: sphinx-rtd-theme >=1.0.0 ; extra == 'docs'
Requires-Dist: myst-parser >=0.18.0 ; extra == 'docs'
